collective.volto.enhancedlinks-1.1.1-py3.10-nspkg.pth
collective/volto/enhancedlinks/__init__.py
collective/volto/enhancedlinks/adapters.py
collective/volto/enhancedlinks/behaviors.zcml
collective/volto/enhancedlinks/configure.zcml
collective/volto/enhancedlinks/indexer.py
collective/volto/enhancedlinks/interfaces.py
collective/volto/enhancedlinks/setuphandlers.py
collective/volto/enhancedlinks/testing.py
collective/volto/enhancedlinks/tool.py
collective/volto/enhancedlinks/upgrades.py
collective/volto/enhancedlinks/upgrades.zcml
collective/volto/enhancedlinks/events/__init__.py
collective/volto/enhancedlinks/events/configure.zcml
collective/volto/enhancedlinks/events/invalidate_cache.py
collective/volto/enhancedlinks/locales/README.rst
collective/volto/enhancedlinks/locales/__init__.py
collective/volto/enhancedlinks/locales/collective.volto.enhancedlinks.pot
collective/volto/enhancedlinks/locales/update.py
collective/volto/enhancedlinks/locales/update.sh
collective/volto/enhancedlinks/locales/en/LC_MESSAGES/collective.volto.enhancedlinks.mo
collective/volto/enhancedlinks/locales/en/LC_MESSAGES/collective.volto.enhancedlinks.po
collective/volto/enhancedlinks/profiles/default/catalog.xml
collective/volto/enhancedlinks/profiles/default/metadata.xml
collective/volto/enhancedlinks/profiles/default/toolset.xml
collective/volto/enhancedlinks/profiles/default/types/File.xml
collective/volto/enhancedlinks/profiles/default/types/Image.xml
collective/volto/enhancedlinks/profiles/uninstall/toolset.xml
collective/volto/enhancedlinks/restapi/__init__.py
collective/volto/enhancedlinks/restapi/configure.zcml
collective/volto/enhancedlinks/restapi/deserializer/__init__.py
collective/volto/enhancedlinks/restapi/deserializer/blocks.py
collective/volto/enhancedlinks/restapi/deserializer/configure.zcml
collective/volto/enhancedlinks/restapi/serializer/__init__.py
collective/volto/enhancedlinks/restapi/serializer/blocks.py
collective.volto.enhancedlinks-1.1.1.dist-info/LICENSE.GPL
collective.volto.enhancedlinks-1.1.1.dist-info/LICENSE.rst
collective.volto.enhancedlinks-1.1.1.dist-info/METADATA
collective.volto.enhancedlinks-1.1.1.dist-info/WHEEL
collective.volto.enhancedlinks-1.1.1.dist-info/entry_points.txt
collective.volto.enhancedlinks-1.1.1.dist-info/namespace_packages.txt
collective.volto.enhancedlinks-1.1.1.dist-info/top_level.txt
collective.volto.enhancedlinks-1.1.1.dist-info/RECORD
